controllers/__init__.py
controllers/myapp.py
data/__init__.py
data/cccache.py
data/config.py
data/redis_sg.py
dofast/__init__.py
dofast/auth.py
dofast/client.py
dofast/concurrency.py
dofast/config.py
dofast/cos.py
dofast/crontasks.py
dofast/fund.py
dofast/logger.py
dofast/network.py
dofast/oss.py
dofast/pipe.py
dofast/qflask.py
dofast/simple_parser.py
dofast/sli_entry.py
dofast/stock.py
dofast/utils.py
dofast/weather.py
dofast/apps/__init__.py
dofast/apps/app.py
dofast/apps/fund.py
dofast/apps/hostoss.py
dofast/apps/roundcorner.py
dofast/apps/sli.py
dofast/apps/urlmanager.py
dofast/base/__init__.py
dofast/base/command.py
dofast/cell/__init__.py
dofast/cell/api.py
dofast/cell/supercell.py
dofast/cli/__init__.py
dofast/cli/slippervideo.py
dofast/core/__init__.py
dofast/core/configuration.py
dofast/data/__init__.py
dofast/data/dynamic.py
dofast/data/msg.py
dofast/db/__init__.py
dofast/db/redis.py
dofast/ext/__init__.py
dofast/ext/cli.py
dofast/jobs/__init__.py
dofast/jobs/apprcn.py
dofast/jobs/skeleton.py
dofast/scripts/__init__.py
dofast/scripts/pyoss.py
dofast/security/__init__.py
dofast/security/_hmac.py
dofast/setups/__init__.py
dofast/setups/fish.py
dofast/toolkits/__init__.py
dofast/toolkits/credit_card_generator.py
dofast/toolkits/file.py
dofast/toolkits/hemabot.py
dofast/toolkits/qredis.py
dofast/toolkits/telegram.py
dofast/toolkits/textparser.py
dofast/toolkits/youdao_dict.py
dofast/vendor/__init__.py
dofast/vendor/command.py
dofast/vendor/graphviz.py
dofast/web/__init__.py
dofast/web/pcloud.py
dofast-1.2.18.dist-info/LICENSE
dofast-1.2.18.dist-info/METADATA
dofast-1.2.18.dist-info/WHEEL
dofast-1.2.18.dist-info/entry_points.txt
dofast-1.2.18.dist-info/top_level.txt
dofast-1.2.18.dist-info/RECORD
