Metadata-Version: 2.1
Name: dofast
Version: 1.2.18
Summary: A package for dirty faster Python programming.
Home-page: https://github.com/GaoangLiu/slipper
Author: GaoangLiu
Author-email: byteleap@gmail.com
Classifier: Programming Language :: Python :: 3
Classifier: License :: OSI Approved :: MIT License
Classifier: Operating System :: OS Independent
License-File: LICENSE
Requires-Dist: codefast (>=0.6.4)
Requires-Dist: fire
Requires-Dist: simauth
Requires-Dist: hashids
Requires-Dist: colorlog (>=4.6.1)
Requires-Dist: tqdm
Requires-Dist: joblib
Requires-Dist: PyGithub
Requires-Dist: oss2
Requires-Dist: lxml
Requires-Dist: cos-python-sdk-v5
Requires-Dist: smart-open
Requires-Dist: pillow
Requires-Dist: bs4
Requires-Dist: arrow
Requires-Dist: redis
Requires-Dist: termcolor
Requires-Dist: python-twitter
Requires-Dist: python-telegram-bot
Requires-Dist: deprecation
Requires-Dist: faker
Requires-Dist: flask
Requires-Dist: pymysql
Requires-Dist: cairosvg (>=2.3.0)
Requires-Dist: jinja2 (>=2.9.3)
Requires-Dist: waitress
Requires-Dist: celery
Requires-Dist: youtube-dl
Requires-Dist: telegraph
